Metadata-Version: 1.1
Name: python-digitalocean-backup
Version: 1.1.0
Summary: Python module to manage Digitalocean droplet backups.
Home-page: https://github.com/corndogcomputers/python-digitalocean-backup
Author: Rob Johnson ( http://corndogcomputers.com )
Author-email: info@corndogcomputers.com
License: The MIT License (MIT)
